nbpresent/__init__.py
nbpresent/_version.py
nbpresent/export.py
nbpresent/exporters/__init__.py
nbpresent/exporters/base.py
nbpresent/exporters/html.py
nbpresent/exporters/pdf.py
nbpresent/exporters/pdf_capture.py
nbpresent/exporters/pdf_ghost.py
nbpresent/static/nbpresent/css/nbpresent.min.css
nbpresent/static/nbpresent/js/nbpresent.deps.min.js
nbpresent/static/nbpresent/js/nbpresent.min.js
nbpresent/static/nbpresent/js/nbpresent.notebook.min.js
nbpresent/static/nbpresent/js/nbpresent.standalone.min.js
nbpresent/static/nbpresent/js/nbpresent.static.min.js
nbpresent/tasks/__init__.py
nbpresent/tasks/_env.py
nbpresent/tasks/build.py
nbpresent/tasks/clean.py
nbpresent/tasks/deps.py
nbpresent/tasks/index.py
nbpresent/tasks/less.py
nbpresent/tasks/notebook.py
nbpresent/tasks/requirejs.py
nbpresent/tasks/standalone.py
nbpresent/templates/nbpresent.tpl
nbpresent/tests/__init__.py
nbpresent/tests/test_export.py
nbpresent/tests/test_notebook.py
nbpresent/tests/js/_utils.js
nbpresent/tests/js/test_export_html.js
nbpresent/tests/js/test_notebook_basic.js
nbpresent/tests/js/test_notebook_create.js
nbpresent/tests/js/test_notebook_no_regions.js
nbpresent/tests/notebooks/Basics.ipynb
nbpresent-3.0.0.dist-info/DESCRIPTION.rst
nbpresent-3.0.0.dist-info/METADATA
nbpresent-3.0.0.dist-info/RECORD
nbpresent-3.0.0.dist-info/WHEEL
nbpresent-3.0.0.dist-info/entry_points.txt
nbpresent-3.0.0.dist-info/metadata.json
nbpresent-3.0.0.dist-info/top_level.txt
