Metadata-Version: 1.1
Name: nbpresent
Version: 3.0.0
Summary: Next generation slides from Jupyter Notebooks
Home-page: https://github.com/Anaconda-Platform/nbpresent
Author: Nicholas Bollweg
Author-email: nbollweg@continuum.io
License: BSD-3-Clause
Keywords: ipython jupyter markdown presentation slides revealjs d3
Platform: UNKNOWN
Classifier: Development Status :: 4 - Beta
Classifier: Framework :: IPython
Classifier: Programming Language :: Python
Classifier: License :: OSI Approved :: BSD License
